seira/__init__.py
seira/masw/__init__.py
seira/masw/dispersionImage.py
seira/masw/plotDispersion.py
seira/tools/__init__.py
seira/tools/segypy.py
seira-1.1.2.dist-info/LICENSE
seira-1.1.2.dist-info/METADATA
seira-1.1.2.dist-info/WHEEL
seira-1.1.2.dist-info/top_level.txt
seira-1.1.2.dist-info/RECORD
