Metadata-Version: 2.1
Name: seira
Version: 1.1.2
Summary: SEIRA: DATA PROCESSING FOR SEISMIC REFRACTION AND MASW
Home-page: UNKNOWN
Author: Putu Pradnya Andika, Tedi Yudistira
Author-email: <putuandhika@hotmail.com>
License: UNKNOWN
Keywords: python,seismic refraction tomography,masw
Platform: UNKNOWN
Classifier: Development Status :: 1 - Planning
Classifier: Intended Audience :: Developers
Classifier: Programming Language :: Python :: 3
Classifier: Operating System :: Unix
Classifier: Operating System :: MacOS :: MacOS X
Classifier: Operating System :: Microsoft :: Windows
License-File: LICENSE
Requires-Dist: numpy
Requires-Dist: matplotlib
